AUTHORS
ChangeLog
Makefile
readme.md
requirements.txt
setup.cfg
setup.py
.vscode/settings.json
.vscode/tags
brewkit/__init__.py
brewkit.egg-info/PKG-INFO
brewkit.egg-info/SOURCES.txt
brewkit.egg-info/dependency_links.txt
brewkit.egg-info/entry_points.txt
brewkit.egg-info/not-zip-safe
brewkit.egg-info/pbr.json
brewkit.egg-info/requires.txt
brewkit.egg-info/top_level.txt
brewkit/api/__init__.py
brewkit/api/configuration.py
brewkit/api/controllers.py
brewkit/api/devices.py
brewkit/api/example_configuration.py
brewkit/api/server.py
brewkit/api/tests/__init__.py
brewkit/api/tests/test_configuration.py
brewkit/api/tests/test_devices.py
brewkit/app/__init__.py
brewkit/app/exceptions.py
brewkit/app/log.py
brewkit/app/omega.py
brewkit/app/str116.py
brewkit/app/tests/__init__.py
brewkit/app/tests/test_omega.py
brewkit/app/tests/test_str116.py
brewkit/docs/Brewkit Project Plan.pdf
brewkit/docs/cli_usage.md
brewkit/docs/api/configuration.md
brewkit/docs/api/controllers_and_devices.md
brewkit/docs/api/lifecycle.md
brewkit/docs/app/omega.md
brewkit/docs/app/str116.md
brewkit/docs/app/str116/bytestring_examples.md
brewkit/docs/app/str116/str116_commands_reference.pdf
brewkit/docs/app/str116/str116_user_guide.pdf
brewkit/interface/__init__.py
brewkit/interface/configure.html
brewkit/interface/index.html
brewkit/interface/css/animate.css
brewkit/interface/css/mdl.css
brewkit/interface/css/styles.css
brewkit/interface/data/configurations.json
brewkit/interface/images/valve.png
brewkit/interface/js/chart_colors.js
brewkit/interface/js/components.js
brewkit/interface/js/configure.js
brewkit/interface/js/index.js
brewkit/interface/js/slack.js
brewkit/interface/js/socket.js
brewkit/interface/js/libs/Chart.bundle.js
brewkit/interface/js/libs/Tock.js
brewkit/interface/js/libs/axios.min.js
brewkit/interface/js/libs/cookie.js
brewkit/interface/js/libs/jquery.min.js
brewkit/interface/js/libs/material.min.js
brewkit/interface/js/libs/socket.io.min.js
brewkit/interface/js/libs/vue.js