Metadata-Version: 1.0
Name: brewkit
Version: 0.0.7
Summary: Brewkit tools
Home-page: http://github.com/NavasotaBrewing/brewkit
Author: Luke Sweeney
Author-email: llamicron@gmail.com
License: MIT
Platform: UNKNOWN
